AUTHORS
BUGS.md
CHANGES.rst
LICENSE
MANIFEST.in
README.rst
TODO.md
setup.py
timemg/__init__.py
timemg/stats.py
timemg.egg-info/PKG-INFO
timemg.egg-info/SOURCES.txt
timemg.egg-info/dependency_links.txt
timemg.egg-info/entry_points.txt
timemg.egg-info/requires.txt
timemg.egg-info/top_level.txt
timemg/data/__init__.py
timemg/data/adverts.py
timemg/io/__init__.py
timemg/io/adverts.py
timemg/io/lock.py
timemg/qt/__init__.py
timemg/qt/main.py
timemg/qt/delegates/__init__.py
timemg/qt/delegates/adverts.py
timemg/qt/models/__init__.py
timemg/qt/models/adverts.py
timemg/qt/widgets/__init__.py
timemg/qt/widgets/mainwindow.py
timemg/qt/widgets/plot.py
timemg/qt/widgets/tabs/__init__.py
timemg/qt/widgets/tabs/adverts.py
timemg/qt/widgets/tabs/stats.py